{
  "iframe": "<iframe width=\"560\" height=\"315\" src=\"https://www.youtube.com/embed/WptKnDQStJk\" frameborder=\"0\" allow=\"accelerometer; autoplay; encrypted-media; gyroscope; picture-in-picture\" allowfullscreen></iframe>",
  "dateshow": "vendredi",
  "thumbnail": "/images/uploads/thanos.jpg",
  "social": [
    {
      "lien": "https://www.facebook.com/Thanos.Karnage/",
      "awesome": "fab fa-facebook-f"
    },
    {
      "lien": "https://soundcloud.com/thanos",
      "awesome": "fab fa-soundcloud "
    },
    {
      "lien": "https://www.facebook.com/theclampsmusic/",
      "awesome": "fab fa-facebook-f"
    },
    {
      "lien": "https://soundcloud.com/the-clamps?fbclid=IwAR1u8WV5Gmmsgn7gqHrKUOw3TmaJl6gk_wZccC1Sguela2a3ISTUq8zcmN0",
      "awesome": "fab fa-soundcloud "
    }
  ],
  "couverture": "/images/uploads/thanos.jpg",
  "date": "22/05/2019",
  "title": "THANOS vs THE CLAMPS",
  "description": "THANOS\n\nThanos découvre la musique techno en Belgique en 1992 et devient l’un des précurseurs de la scène techno hardcore en France et à travers l'Europe. Il fonde en 1996 FRAKTAL avec Matt FRAKTAL et Fred ANTICORE.\n\nAujourd'hui il reste un des principaux activistes de la scène hardcore, nous offrant des mixes à tendance « indus », avec une préférence pour les basses fortes et puissantes  \n\n\n\nTHE CLAMPS\n\nAprès avoir découvert sa passion à la fin des années 90, Julien Carbou, alias The Clamps, a perfectionné ses productions dans plusieurs projets musicaux allant de la Hard Techno à la Drum and Bass. The Clamps commence à grandir à travers le label français Kosen Production. Leur amitié donnera naissance à de belles sorties en solo et à des collaborations avec Redject ou NickBee.",
  "stage": "HARDCORE"
}